mlmt/__init__.py
mlmt/io.py
mlmt/logger.py
mlmt/model.py
mlmt/running_stats.py
mlmt/time_stamp.py
mlmt/tool.py
mlmt-0.0.5.dist-info/LICENSE
mlmt-0.0.5.dist-info/WHEEL
mlmt-0.0.5.dist-info/METADATA
mlmt-0.0.5.dist-info/RECORD
